setup.py
src/mdnsbrowser
src/mdnsbrowser.py
src/mdns_browser/__init__.py
src/mdns_browser/agents/__init__.py
src/mdns_browser/agents/cache.py
src/mdns_browser/agents/comms.py
src/mdns_browser/agents/debug.py
src/mdns_browser/agents/listener.py
src/mdns_browser/agents/logger.py
src/mdns_browser/agents/querier.py
src/mdns_browser/agents/sup.py
src/mdns_browser/agents/tray.py
src/mdns_browser/agents/ui.py
src/mdns_browser/agents/uitk.py
src/mdns_browser/mdns/__init__.py
src/mdns_browser/system/__init__.py
src/mdns_browser/system/base.py
src/mdns_browser/system/config.py
src/mdns_browser/system/mswitch.py
src/mdns_browser/system/ui_base.py
src/mdnsbrowser.egg-info/PKG-INFO
src/mdnsbrowser.egg-info/SOURCES.txt
src/mdnsbrowser.egg-info/dependency_links.txt
src/mdnsbrowser.egg-info/not-zip-safe
src/mdnsbrowser.egg-info/top_level.txt