Metadata-Version: 1.0
Name: mdnsbrowser
Version: 0.4.1
Summary: Multicast DNS service browser
Home-page: http://www.systemical.com/doc/opensource
Author: Jean-Lou Dupont
Author-email: jl@jldupont.com
License: UNKNOWN
Platform: UNKNOWN
